ms_image_gen_mcp/__init__.py
ms_image_gen_mcp/__main__.py
ms_image_gen_mcp/server.py
ms_image_gen_mcp-1.3.0.dist-info/METADATA
ms_image_gen_mcp-1.3.0.dist-info/WHEEL
ms_image_gen_mcp-1.3.0.dist-info/entry_points.txt
ms_image_gen_mcp-1.3.0.dist-info/RECORD
