Metadata-Version: 2.4
Name: ms-image-gen-mcp
Version: 1.3.0
Summary: ModelScope Image Generator
Requires-Python: >=3.12
Requires-Dist: build>=1.2.2.post1
Requires-Dist: mcp[cli]>=1.11.0
Requires-Dist: requests>=2.32.3
Requires-Dist: twine>=6.1.0
